pyobistools/__init__.py
pyobistools/taxa.py
pyobistools/utils.py
pyobistools/validation/__init__.py
pyobistools/validation/check_eventids.py
pyobistools/validation/check_fields.py
pyobistools/validation/check_onland.py
pyobistools/validation/check_scientificname_and_ids.py
pyobistools-1.0.0.dist-info/LICENSE
pyobistools-1.0.0.dist-info/METADATA
pyobistools-1.0.0.dist-info/WHEEL
pyobistools-1.0.0.dist-info/top_level.txt
pyobistools-1.0.0.dist-info/RECORD
