Metadata-Version: 2.1
Name: pyobistools
Version: 1.0.0
Summary: Python tools for quality-controlling data for publishing to OBIS
Home-page: https://github.com/cioos-siooc/pyobistools
License: BSD-3-Clause
Classifier: Development Status :: 5 - Production/Stable
Classifier: Intended Audience :: Developers
Classifier: Intended Audience :: Science/Research
Classifier: Programming Language :: Python
Classifier: Programming Language :: Python :: 3.7
Classifier: Programming Language :: Python :: 3.8
Classifier: Programming Language :: Python :: 3.9
Classifier: Programming Language :: Python :: 3.10
Classifier: Topic :: Scientific/Engineering
Classifier: Topic :: Scientific/Engineering :: GIS
Classifier: Topic :: Scientific/Engineering :: Information Analysis
Requires-Python: <4,>=3.7
License-File: LICENSE
Requires-Dist: pandas <=1.5.3,>=1.3.5
Requires-Dist: geopandas
Requires-Dist: pyworms <1.0,>=0.2.0
Requires-Dist: pyxylookup
Requires-Dist: cartopy
